README.md
setup.py
multiprocess_logger/__init__.py
multiprocess_logger/handler.py
multiprocess_logger/test_handler.py
multiprocess_logger.egg-info/PKG-INFO
multiprocess_logger.egg-info/SOURCES.txt
multiprocess_logger.egg-info/dependency_links.txt
multiprocess_logger.egg-info/top_level.txt