Metadata-Version: 2.1
Name: multiprocess-logger
Version: 0.3
Summary: 一个安全可靠高效的进程间日志处理器  A safe, reliable and efficient inter process log processor 修复描述
Home-page: https://gitee.com
Author: liuyancong
Author-email: lyc456789@163.com
License: UNKNOWN
Platform: UNKNOWN
Classifier: Programming Language :: Python :: 3
Classifier: License :: OSI Approved :: MIT License
Classifier: Operating System :: OS Independent
Requires-Python: >=3.5
